pyespn/__init__.py
pyespn/api/__init__.py
pyespn/api/version.py
pyespn/bin/__init__.py
pyespn/bin/sports/__init__.py
pyespn/bin/sports/sports.py
pyespn/classes/__init__.py
pyespn/classes/betting.py
pyespn/classes/draft.py
pyespn/classes/event.py
pyespn/classes/gamelog.py
pyespn/classes/image.py
pyespn/classes/league.py
pyespn/classes/player.py
pyespn/classes/schedule.py
pyespn/classes/standings.py
pyespn/classes/stat.py
pyespn/classes/team.py
pyespn/classes/vehicle.py
pyespn/classes/venue.py
pyespn/core/__init__.py
pyespn/core/awards.py
pyespn/core/betting.py
pyespn/core/client.py
pyespn/core/decorators.py
pyespn/core/draft.py
pyespn/core/games.py
pyespn/core/leagues.py
pyespn/core/orchestration.py
pyespn/core/players.py
pyespn/core/recruiting.py
pyespn/core/schedule.py
pyespn/core/standings.py
pyespn/core/teams.py
pyespn/data/__init__.py
pyespn/data/betting.py
pyespn/data/data_import.py
pyespn/data/leagues.py
pyespn/data/standings.py
pyespn/data/teams.py
pyespn/data/version.py
pyespn/data/files/__init__.py
pyespn/data/files/college_teams_lookup.json
pyespn/data/files/epl_teams_ints.json
pyespn/data/files/f1_teams_lookup.json
pyespn/data/files/indy_teams_lookup.json
pyespn/data/files/mlb_teams_lookup.json
pyespn/data/files/nascar_teams_lookup.json
pyespn/data/files/nba_teams_lookup.json
pyespn/data/files/nfl_teams_lookup.json
pyespn/data/files/wnba_teams_lookup.json
pyespn/exceptions/__init__.py
pyespn/exceptions/api.py
pyespn/exceptions/classes.py
pyespn/exceptions/leagues.py
pyespn/exceptions/schedules.py
pyespn/sports/__init__.py
pyespn/sports/sports.py
pyespn/utilities/__init__.py
pyespn/utilities/api.py
pyespn/utilities/finds.py
pyespn/utilities/strings.py
pyespn/utilities/urls.py
pyespn-0.3.3.dist-info/LICENSE
pyespn-0.3.3.dist-info/METADATA
pyespn-0.3.3.dist-info/WHEEL
pyespn-0.3.3.dist-info/entry_points.txt
pyespn-0.3.3.dist-info/top_level.txt
pyespn-0.3.3.dist-info/RECORD
