Metadata-Version: 2.1
Name: pyespn
Version: 0.3.3
Summary: Wrapper for hidden ESPN API
Author: Zach
Author-email: Zach Stocker <zacharystocker@gmail.com>
License: MIT
Project-URL: Repository, https://github.com/EnderLocke/pyespn
Classifier: Development Status :: 4 - Beta
Classifier: Intended Audience :: Developers
Classifier: License :: OSI Approved :: MIT License
Classifier: Programming Language :: Python
Classifier: Programming Language :: Python :: 3.11
Requires-Python: >=3.11
License-File: LICENSE
Requires-Dist: click>=8.1.8
Requires-Dist: mkdocs>=1.6.1
Requires-Dist: mkdocs-material>=9.6.7
Requires-Dist: mkdocstrings>=0.29.1
Requires-Dist: mkdocstrings-python>=1.16.8
Requires-Dist: requests>=2.32.3
Requires-Dist: tqdm>=4.67.1
